my_calculator/__init__.py
my_calculator/my_calculator.py
cds4_computation-0.1.dist-info/LICENSE.txt
cds4_computation-0.1.dist-info/METADATA
cds4_computation-0.1.dist-info/WHEEL
cds4_computation-0.1.dist-info/top_level.txt
cds4_computation-0.1.dist-info/RECORD
