Metadata-Version: 2.1
Name: cds4-computation
Version: 0.1
Summary: Several calculations of two numbers
Home-page: UNKNOWN
Author: Urmila
License: UNKNOWN
Platform: UNKNOWN
License-File: LICENSE.txt
